{
    "mode": 0,
    "oformat": "netcdf4",
    "deflate": 4,
    "atmocor": 1,
    "proc_ocean": 1,
    "proc_land": 1,
    "proc_sst": 0,
    "aer_opt": -17,
    "aer_swir_short": -1,
    "aer_swir_long": -1,
    "aer_rrs_short": -1.0,
    "aer_rrs_long": -1.0,
    "aer_iter_max": 10,
    "rhoamin": 0.0002,
    "gas_opt": 15,
    "pol_opt": 0,
    "brdf_opt": 7,
    "glint_opt": 1,
    "outband_opt": 2,
    "oxaband_opt": 0,
    "filter_opt": 0,
    "absaer_opt": 0,
    "seawater_opt": 1,
    "demfile": "$OCDATAROOT/common/gebco_ocssw_v2020.nc",
    "anc_cor_file": "$OCDATAROOT/common/anc_cor_file_28jan2014.nc",
    "met1": "$OCDATAROOT/common/met_climatology_v2014.hdf",
    "ozone1": "$OCDATAROOT/common/ozone_climatology_v2014.hdf",
    "no2file": "$OCDATAROOT/common/no2_climatology_v2013.hdf",
    "land": "$OCDATAROOT/common/gebco_ocssw_v2020.nc",
    "water": "$OCDATAROOT/common/gebco_ocssw_v2020.nc",
    "icefile": "$OCDATAROOT/common/ice_climatology.hdf",
    "sssfile": "$OCDATAROOT/common/sss_climatology_woa2009.hdf",
    "sstfile": "$OCDATAROOT/common/sst_climatology.hdf",
    "sstrefdif": 1.25,
    "alphafile": "$OCDATAROOT/common/alpha510_climatology.hdf",
    "tauafile": "$OCDATAROOT/common/taua865_climatology.hdf",
    "fqfile": "$OCDATAROOT/common/morel_fq.nc",
    "water_spectra_file": "$OCDATAROOT/common/water_spectra.nc",
    "mldfile": "$OCDATAROOT/common/mld_climatology_woa1994.hdf",
    "spixl": 1,
    "epixl": -1,
    "dpixl": 1,
    "sline": 1,
    "eline": -1,
    "dline": 1,
    "wsmax": 12.0,
    "picfile": "$OCDATAROOT/common/calcite_table-20170109.txt",
    "giop_fit_opt": 1,
    "giop_rrs_opt": 0,
    "giop_aph_opt": 2,
    "giop_adg_opt": 1,
    "giop_adg_s": 0.018,
    "giop_bbp_opt": 3,
    "iop_opt": 0,
    "raman_opt": 2,
    "albedo": 0.027,
    "absaer": 0.0,
    "nlwmin": 0.15,
    "tauamax": 0.3,
    "epsmin": 0.80,
    "epsmax": 1.35,
    "glint": 0.005,
    "sunzen": 70.0,
    "satzen": 60.0,
    "windspeed": -1000,
    "windangle": -1000,
    "pressure": -1000,
    "ozone": -1000,
    "watervapor": -1000,
    "relhumid": -1000,
    "maskland": 1,
    "maskbath": 0,
    "maskcloud": 1,
    "maskglint": 0,
    "masksunzen": 0,
    "masksatzen": 0,
    "maskhilt": 1,
    "maskstlight": 0
}